{
	"info": {
		"_postman_id": "98594507-2dba-4e6f-966b-07f52d5ff192",
		"name": "Products_API",
		"schema": "https://schema.getpostman.com/json/collection/v2.1.0/collection.json",
		"_exporter_id": "22976240"
	},
	"item": [
		{
			"name": "Get_All_Products",
			"request": {
				"method": "GET",
				"header": [],
				"url": {
					"raw": "http://127.0.0.1:8000/api/products/",
					"protocol": "http",
					"host": [
						"127",
						"0",
						"0",
						"1"
					],
					"port": "8000",
					"path": [
						"api",
						"products",
						""
					]
				}
			},
			"response": []
		},
		{
			"name": "Create_Product",
			"request": {
				"method": "POST",
				"header": [],
				"body": {
					"mode": "raw",
					"raw": "{\r\n    \"title\": \"Optimus Backpacking Cookset\",\r\n    \"description\": \"A lightweight, aluminum pot with 650 ml capacity and a lightweight stove attachment that fits most butane/propane mix canisters.\",\r\n    \"price\": \"65.00\",\r\n    \"inventory_quantity\": 2\r\n    }",
					"options": {
						"raw": {
							"language": "json"
						}
					}
				},
				"url": {
					"raw": "http://127.0.0.1:8000/api/products/",
					"protocol": "http",
					"host": [
						"127",
						"0",
						"0",
						"1"
					],
					"port": "8000",
					"path": [
						"api",
						"products",
						""
					]
				}
			},
			"response": []
		},
		{
			"name": "Get_Product_By_Id",
			"request": {
				"method": "GET",
				"header": [],
				"url": {
					"raw": "http://127.0.0.1:8000/api/products/1/",
					"protocol": "http",
					"host": [
						"127",
						"0",
						"0",
						"1"
					],
					"port": "8000",
					"path": [
						"api",
						"products",
						"1",
						""
					]
				}
			},
			"response": []
		},
		{
			"name": "Update_Product",
			"request": {
				"method": "PUT",
				"header": [],
				"body": {
					"mode": "raw",
					"raw": " {\r\n    \"title\": \"Leuko Tape\",\r\n    \"description\": \"A must have form of blister prevention and care. If applied to the skin when dry, it will perhaps never come off without human intervention\",\r\n    \"price\": 10.00,\r\n    \"inventory_quantity\": 4\r\n}",
					"options": {
						"raw": {
							"language": "json"
						}
					}
				},
				"url": {
					"raw": "http://127.0.0.1:8000/api/products/4/",
					"protocol": "http",
					"host": [
						"127",
						"0",
						"0",
						"1"
					],
					"port": "8000",
					"path": [
						"api",
						"products",
						"4",
						""
					]
				}
			},
			"response": []
		},
		{
			"name": "Delete_Product",
			"request": {
				"method": "DELETE",
				"header": [],
				"url": {
					"raw": "http://127.0.0.1:8000/api/products/5/",
					"protocol": "http",
					"host": [
						"127",
						"0",
						"0",
						"1"
					],
					"port": "8000",
					"path": [
						"api",
						"products",
						"5",
						""
					]
				}
			},
			"response": []
		}
	]
}